setup.cfg
setup.py
quant_trading/__init__.py
quant_trading/api_client.py
quant_trading/configuration.py
quant_trading/rest.py
quant_trading/api/__init__.py
quant_trading/api/bitcoin_futures_manager_api.py
quant_trading/api/bitcoin_futures_market_maker_api.py
quant_trading/api/bitcoin_futures_swinger_api.py
quant_trading/models/__init__.py
quant_trading/models/algo_params_response.py
quant_trading/models/avg_open_position_hours.py
quant_trading/models/closed_position_hours.py
quant_trading/models/current_position_pct.py
quant_trading/models/current_unrealised_pct.py
quant_trading/models/error.py
quant_trading/models/exec_algo_response.py
quant_trading/models/exec_position_manager_algo_request.py
quant_trading/models/exec_position_swinger_algo_request.py
quant_trading/models/last_open_stake_hours.py
quant_trading/models/open_position_hours.py
quant_trading/models/position_state.py
quant_trading/models/stake_state.py
quant_trading/models/x_rate_limit_limit.py
quant_trading/models/x_rate_limit_remaining.py
quant_trading/models/x_rate_limit_reset.py
quant_trading_api.egg-info/PKG-INFO
quant_trading_api.egg-info/SOURCES.txt
quant_trading_api.egg-info/dependency_links.txt
quant_trading_api.egg-info/requires.txt
quant_trading_api.egg-info/top_level.txt